helloworld/app.py
helloworld/test.py
mibrahim_helloworld_2019-0.1.1.dist-info/LICENCE
mibrahim_helloworld_2019-0.1.1.dist-info/METADATA
mibrahim_helloworld_2019-0.1.1.dist-info/WHEEL
mibrahim_helloworld_2019-0.1.1.dist-info/top_level.txt
mibrahim_helloworld_2019-0.1.1.dist-info/RECORD
